README.md
export_data.py
setup.py
wandb2numpy/__init__.py
wandb2numpy/command_line.py
wandb2numpy/config_loader.py
wandb2numpy/export.py
wandb2numpy/filtering.py
wandb2numpy/save_experiment.py
wandb2numpy/util.py
wandb2numpy.egg-info/PKG-INFO
wandb2numpy.egg-info/SOURCES.txt
wandb2numpy.egg-info/dependency_links.txt
wandb2numpy.egg-info/entry_points.txt
wandb2numpy.egg-info/requires.txt
wandb2numpy.egg-info/top_level.txt